example.sv
`timescale 1ns/1ps

module example(
    input  logic a, b, c,
    output logic y
);
    logic ab, bb, cb, n1, n2, n3;

    // Invert inputs after 1 time unit delay
    assign #1 {ab, bb, cb} = ~{a, b, c};

    // Some logic expressions with 2 time unit delay
    assign #2 n1 = ab & bb & cb;
    assign #2 n2 = a & bb & cb;
    assign #2 n3 = a & bb & c;

    // Output y after 4 time unit delay
    assign #4 y = n1 | n2 | n3;
endmodule

tb_example.sv
`timescale 1ns/1ps

module tb_example;
    logic a, b, c;
    logic y;

    // Instantiate the design under test (DUT)
    example dut (
        .a(a), .b(b), .c(c), .y(y)
    );

    initial begin
        $dumpfile("example.vcd");   // waveform dump file
        $dumpvars(0, tb_example);   // dump all variables

        // Apply test values
        a = 0; b = 0; c = 0;
        #10;
        a = 1; b = 0; c = 1;
        #10;
        a = 1; b = 1; c = 0;
        #10;
        a = 1; b = 1; c = 1;
        #10;

        $finish;
    end
endmodule

example - Copy.vcd
$date
	Mon Aug 18 19:00:59 2025
$end
$version
	Icarus Verilog
$end
$timescale
	1ps
$end
$scope module tb_example $end
$var wire 1 ! y $end
$var reg 1 " a $end
$var reg 1 # b $end
$var reg 1 $ c $end
$scope module dut $end
$var wire 1 " a $end
$var wire 1 # b $end
$var wire 1 $ c $end
$var wire 1 % n1 $end
$var wire 1 & n2 $end
$var wire 1 ' n3 $end
$var wire 1 ! y $end
$var wire 1 ( cb $end
$var wire 1 ) bb $end
$var wire 1 * ab $end
$upscope $end
$upscope $end
$enddefinitions $end
$comment Show the parameter values. $end
$dumpall
$end
#0
$dumpvars
x*
x)
x(
x'
x&
x%
0$
0#
0"
x!
$end
#1000
1*
1)
1(
#2000
0'
0&
#3000
1%
#7000
1!
#10000
1$
1"
#11000
0*
0(
#12000
1'
#13000
0%
#20000
0$
1#
#21000
0)
1(
#22000
0'
#26000
0!
#30000
1$
#31000
0(
