moorefsmcounter.sv
module moore_counter (
    input clk,
    input reset,
    output reg [1:0] count
);
    // State encoding
    parameter S0 = 2'b00;
    parameter S1 = 2'b01;
    parameter S2 = 2'b10;
    parameter S3 = 2'b11;

    reg [1:0] state, next_state;

    // Sequential block
    always @(posedge clk or posedge reset) begin
        if (reset)
            state <= S0;
        else
            state <= next_state;
    end

    // Next state logic
    always @(*) begin
        case(state)
            S0: next_state = S1;
            S1: next_state = S2;
            S2: next_state = S3;
            S3: next_state = S0;
            default: next_state = S0;
        endcase
    end

    // Output logic (Moore: depends only on state)
    always @(*) begin
        case(state)
            S0: count = 2'b00;
            S1: count = 2'b01;
            S2: count = 2'b10;
            S3: count = 2'b11;
            default: count = 2'b00;
        endcase
    end
endmodule

tb_moorefsmcounter.sv
`timescale 1ns/1ps
module tb_moore_counter;
    reg clk, reset;
    wire [1:0] count;

    // Instantiate DUT
    moore_counter uut (
        .clk(clk),
        .reset(reset),
        .count(count)
    );

    // Clock generator
    initial begin
        clk = 0;
        forever #5 clk = ~clk; // 10ns period
    end

    // Stimulus
    initial begin
        $dumpfile("moore_counter.vcd");
        $dumpvars(0, tb_moore_counter);

        reset = 1;
        #10 reset = 0;

        #100; // Run simulation for 100ns
        $finish;
    end

    // Monitor
    initial begin
        $monitor("Time=%0t | reset=%b | state_out=%b", $time, reset, count);
    end
endmodule

moore_counter.vcd
$date
	Wed Aug 20 01:05:13 2025
$end
$version
	Icarus Verilog
$end
$timescale
	1ps
$end
$scope module tb_moore_counter $end
$var wire 2 ! count [1:0] $end
$var reg 1 " clk $end
$var reg 1 # reset $end
$scope module uut $end
$var wire 1 " clk $end
$var wire 1 # reset $end
$var parameter 2 $ S0 $end
$var parameter 2 % S1 $end
$var parameter 2 & S2 $end
$var parameter 2 ' S3 $end
$var reg 2 ( count [1:0] $end
$var reg 2 ) next_state [1:0] $end
$var reg 2 * state [1:0] $end
$upscope $end
$upscope $end
$enddefinitions $end
$comment Show the parameter values. $end
$dumpall
b11 '
b10 &
b1 %
b0 $
$end
#0
$dumpvars
b0 *
b1 )
b0 (
1#
0"
b0 !
$end
#5000
1"
#10000
0"
0#
#15000
b10 )
b1 !
b1 (
b1 *
1"
#20000
0"
#25000
b10 !
b10 (
b11 )
b10 *
1"
#30000
0"
#35000
b0 )
b11 !
b11 (
b11 *
1"
#40000
0"
#45000
b0 !
b0 (
b1 )
b0 *
1"
#50000
0"
#55000
b10 )
b1 !
b1 (
b1 *
1"
#60000
0"
#65000
b10 !
b10 (
b11 )
b10 *
1"
#70000
0"
#75000
b0 )
b11 !
b11 (
b11 *
1"
#80000
0"
#85000
b0 !
b0 (
b1 )
b0 *
1"
#90000
0"
#95000
b10 )
b1 !
b1 (
b1 *
1"
#100000
0"
#105000
b10 !
b10 (
b11 )
b10 *
1"
